wbpFonttools/__init__.py
wbpFonttools/config.py
wbpFonttools/control.py
wbpFonttools/dialog.py
wbpFonttools/document.py
wbpFonttools/selectFontsDialogUI.py
wbpFonttools/template.py
wbpFonttools/tools.py
wbpFonttools/view.py
wbpFonttools/window.py
wbpFonttools/windowUI.py
wbpFonttools-0.2.6.dist-info/LICENSE
wbpFonttools-0.2.6.dist-info/METADATA
wbpFonttools-0.2.6.dist-info/WHEEL
wbpFonttools-0.2.6.dist-info/entry_points.txt
wbpFonttools-0.2.6.dist-info/top_level.txt
wbpFonttools-0.2.6.dist-info/RECORD
